[{"version": "autorx-1.4.0", "humidity": "83.2", "time": "22:25:52", "@timestamp": "2021-02-06T23:50:09.194Z", "uploader_callsign": "KS_AUTO_RX", "comment": "IMET IMET-5835022F 402.998 MHz 904.2hPa 5.2V", "lat": "50.75966", "time_uploaded": "2021-01-30T22:25:37.335002Z", "lon": "4.76939", "alt": "793", "vel_h": "0.0", "type": "iMet-4", "frame": "951", "datetime": "2021-01-30T22:25:37.335002Z", "log_date": "2021-01", "serial": "IMET-5835022F", "temp": "-0.3", "@version": "1", "checksum": "68D3\\n'", "launch_site": "06458", "launch_site_range_estimate": 1614.2021764663316}, {"version": "autorx-1.4.0", "humidity": "1.4", "time": "23:41:45", "@timestamp": "2021-02-06T23:49:17.462Z", "uploader_callsign": "PE1MIU-11", "comment": "IMET IMET-5835022F 402.999 MHz 52.4hPa 3.8V", "lat": "50.41895", "time_uploaded": "2021-01-30T23:41:30.150766Z", "lon": "5.32625", "alt": "19876", "vel_h": "0.0", "type": "iMet-4", "frame": "5504", "datetime": "2021-01-30T23:41:30.150766Z", "log_date": "2021-01", "serial": "IMET-5835022F", "temp": "-58.7", "@version": "1", "checksum": "B65F\\n'", "launch_site": "06458", "launch_site_range_estimate": 1614.2021764663316}, {"version": "autorx-1.4.0", "humidity": "100.0", "time": "00:12:14", "@timestamp": "2021-02-06T23:49:13.747Z", "uploader_callsign": "ON3RC-2_AUTO_RX", "comment": "IMET IMET-5835022F 402.998 MHz 860.0hPa 3.8V", "lat": "50.27744", "time_uploaded": "2021-01-31T00:12:00.121888Z", "lon": "5.56637", "alt": "1244", "vel_h": "0.0", "type": "iMet-4", "frame": "7333", "datetime": "2021-01-31T00:12:00.121888Z", "log_date": "2021-01", "serial": "IMET-5835022F", "temp": "-0.4", "@version": "1", "checksum": "3160\\n'", "launch_site": "06458", "launch_site_range_estimate": 1614.2021764663316}]