[{"version": "autorx-1.4.0", "humidity": "12.4", "time": "00:24:54", "@timestamp": "2021-02-06T21:58:17.009Z", "uploader_callsign": "M0EYT", "comment": "M10 M10-908-2-10293 403.999 MHz 5.3V", "lat": "48.18926", "time_uploaded": "2021-01-06T00:25:06.913232Z", "lon": "-4.45382", "alt": "18892", "vel_h": "11.8", "type": "payload_telemetry", "frame": "1293927912", "datetime": "2021-01-06T00:25:06.913232Z", "log_date": "2021-01", "serial": "M10-908-2-10293", "temp": "-63.0", "@version": "1", "checksum": "1CC5\\n'"}, {"version": "autorx-1.4.0", "humidity": "2.7", "time": "02:10:29", "@timestamp": "2021-02-06T21:59:19.049Z", "uploader_callsign": "F4EZO", "comment": "M10 M10-908-2-10293 403.994 MHz 3.5V", "lat": "47.42379", "time_uploaded": "2021-01-06T02:10:30.077238Z", "lon": "-1.84542", "alt": "35108", "vel_h": "28.9", "type": "payload_telemetry", "frame": "1293934247", "datetime": "2021-01-06T02:10:30.077238Z", "log_date": "2021-01", "serial": "M10-908-2-10293", "temp": "-43.5", "@version": "1", "checksum": "6906\\n'"}, {"version": "autorx-1.4.0", "humidity": "2.2", "time": "02:13:45", "@timestamp": "2021-02-06T23:40:53.425Z", "uploader_callsign": "THIERRY", "comment": "M10 M10-908-2-10293 403.995 MHz 3.4V", "lat": "47.39946", "time_uploaded": "2021-01-06T02:14:00.147634Z", "lon": "-1.77503", "alt": "35037", "vel_h": "32.2", "type": "payload_telemetry", "frame": "1293934443", "datetime": "2021-01-06T02:14:00.147634Z", "log_date": "2021-01", "serial": "M10-908-2-10293", "temp": "-45.6", "@version": "1", "checksum": "32D0\\n'"}]