[{"version": "autorx-1.1.2", "humidity": "-1.0", "time": "00:04:15", "@timestamp": "2021-02-06T23:47:42.264Z", "uploader_callsign": "PU5MLT-6", "comment": "RS41 S1820237 402.990 MHz", "lat": "-25.66351", "time_uploaded": "2021-01-07T00:04:00.090528Z", "lon": "-54.35890", "alt": "8393", "vel_h": "23.4", "type": "payload_telemetry", "frame": "2071", "datetime": "2021-01-07T00:04:00.090528Z", "log_date": "2021-01", "serial": "S1820237", "temp": "-273.0", "@version": "1", "checksum": "02A1\\n'"}, {"version": "autorx-1.1.2", "humidity": "-1.0", "time": "00:56:43", "@timestamp": "2021-02-06T23:55:55.781Z", "uploader_callsign": "PU5MLT-6", "comment": "RS41 S1820237 402.990 MHz", "lat": "-25.82769", "time_uploaded": "2021-01-07T00:56:30.087220Z", "lon": "-54.17978", "alt": "21866", "vel_h": "12.8", "type": "payload_telemetry", "frame": "5219", "datetime": "2021-01-07T00:56:30.087220Z", "log_date": "2021-01", "serial": "S1820237", "temp": "-273.0", "@version": "1", "checksum": "0CE4\\n'"}, {"version": "autorx-1.1.2", "humidity": "82.1", "time": "02:13:25", "@timestamp": "2021-02-06T23:48:20.854Z", "uploader_callsign": "PU5MLT-6", "comment": "RS41-SGP S1820237 402.990 MHz", "lat": "-26.00060", "time_uploaded": "2021-01-07T02:13:30.087036Z", "lon": "-53.97491", "alt": "9386", "vel_h": "19.8", "type": "payload_telemetry", "frame": "9821", "datetime": "2021-01-07T02:13:30.087036Z", "log_date": "2021-01", "serial": "S1820237", "temp": "-28.1", "@version": "1", "checksum": "A9F9\\n'"}]