[{"version": "autorx-1.4.0", "humidity": "-1.0", "time": "12:10:13", "@timestamp": "2021-02-07T00:01:32.446Z", "uploader_callsign": "PY1TCM", "comment": "RS41 R3951348 405.302 MHz 2.9V", "lat": "-22.83457", "time_uploaded": "2021-01-22T12:09:57.276365Z", "lon": "-43.27016", "alt": "11986", "vel_h": "11.3", "type": "payload_telemetry", "frame": "4992", "datetime": "2021-01-22T12:09:57.276365Z", "log_date": "2021-01", "serial": "R3951348", "temp": "-273.0", "@version": "1", "checksum": "3ACA\\n'"}, {"version": "autorx-1.4.0", "humidity": "1.5", "time": "12:43:45", "@timestamp": "2021-02-07T00:01:20.492Z", "uploader_callsign": "PY1TCM", "comment": "RS41-SGP R3951348 405.302 MHz 22.9hPa 2.7V", "lat": "-22.78161", "time_uploaded": "2021-01-22T12:43:30.116586Z", "lon": "-43.39969", "alt": "25519", "vel_h": "19.5", "type": "payload_telemetry", "frame": "7004", "datetime": "2021-01-22T12:43:30.116586Z", "log_date": "2021-01", "serial": "R3951348", "temp": "-56.1", "@version": "1", "checksum": "DD0E\\n'"}, {"version": "autorx-1.4.0", "humidity": "-1.0", "time": "13:06:35", "@timestamp": "2021-02-07T00:01:23.012Z", "uploader_callsign": "PY1TCM", "comment": "RS41 R3951348 405.302 MHz BT 08:08:53 2.6V", "lat": "-22.76587", "time_uploaded": "2021-01-22T13:06:30.137947Z", "lon": "-43.44475", "alt": "5452", "vel_h": "1.8", "type": "payload_telemetry", "frame": "8374", "datetime": "2021-01-22T13:06:30.137947Z", "log_date": "2021-01", "serial": "R3951348", "temp": "-273.0", "@version": "1", "checksum": "5907\\n'"}]