[{"version": "autorx-1.4.0", "humidity": "-1.0", "time": "11:40:46", "@timestamp": "2021-02-06T23:48:55.045Z", "uploader_callsign": "OH8GOU_AUTO_RX", "comment": "RS41 S1020003 404.000 MHz 2.8V", "lat": "67.41818", "time_uploaded": "2021-01-22T11:40:30.269633Z", "lon": "26.54077", "alt": "3385", "vel_h": "11.4", "type": "RS41", "frame": "2175", "datetime": "2021-01-22T11:40:30.269633Z", "log_date": "2021-01", "serial": "S1020003", "temp": "-273.0", "@version": "1", "checksum": "ED6F\\n'", "launch_site": "02836", "launch_site_range_estimate": 6846.176554458369}, {"version": "autorx-1.4.0", "humidity": "2.1", "time": "13:06:15", "@timestamp": "2021-02-06T23:54:48.441Z", "uploader_callsign": "OH8GOU_AUTO_RX", "comment": "RS41-SG S1020003 404.000 MHz 2.5V", "lat": "67.17319", "time_uploaded": "2021-01-22T13:06:00.098800Z", "lon": "25.73510", "alt": "30601", "vel_h": "31.3", "type": "RS41", "frame": "7304", "datetime": "2021-01-22T13:06:00.098800Z", "log_date": "2021-01", "serial": "S1020003", "temp": "-51.3", "@version": "1", "checksum": "5F49\\n'", "launch_site": "02836", "launch_site_range_estimate": 6846.176554458369}, {"version": "autorx-1.4.0", "humidity": "69.4", "time": "13:31:15", "@timestamp": "2021-02-07T00:01:34.931Z", "uploader_callsign": "OH8GOU_AUTO_RX", "comment": "RS41-SG S1020003 404.000 MHz BT 08:06:11 2.5V", "lat": "67.12916", "time_uploaded": "2021-01-22T13:31:00.018283Z", "lon": "25.78493", "alt": "3342", "vel_h": "7.2", "type": "RS41", "frame": "8804", "datetime": "2021-01-22T13:31:00.018283Z", "log_date": "2021-01", "serial": "S1020003", "temp": "-20.7", "@version": "1", "checksum": "FB92\\n'", "launch_site": "02836", "launch_site_range_estimate": 6846.176554458369}]