[{"version": "autorx-1.4.0", "humidity": "-1.0", "time": "11:33:16", "@timestamp": "2021-02-06T16:44:28.453Z", "uploader_callsign": "OH1ZJ_AUTO_RX", "comment": "RS41 S1031072 403.000 MHz 2.9V", "lat": "60.81346", "time_uploaded": "2021-01-09T11:33:00.206930Z", "lon": "23.49282", "alt": "1088", "vel_h": "2.4", "type": "RS41", "frame": "1734", "datetime": "2021-01-09T11:33:00.206930Z", "log_date": "2021-01", "serial": "S1031072", "temp": "-273.0", "@version": "1", "checksum": "957D\\n'", "launch_site": "02963", "launch_site_range_estimate": 342.78539601957056}, {"version": "autorx-1.1.3.3", "humidity": "3.5", "time": "12:47:25", "@timestamp": "2021-02-06T23:25:21.996Z", "uploader_callsign": "OH3RAMI_AUTO_RX", "comment": "RS41-SG S1031072 402.980 MHz", "lat": "60.83939", "time_uploaded": "2021-01-09T12:47:10.119682Z", "lon": "24.04849", "alt": "25691", "vel_h": "16.8", "type": "RS41", "frame": "6183", "datetime": "2021-01-09T12:47:10.119682Z", "log_date": "2021-01", "serial": "S1031072", "temp": "-72.5", "@version": "1", "checksum": "8DA1\\n'", "launch_site": "02963", "launch_site_range_estimate": 342.78539601957056}, {"version": "autorx-1.3.2", "humidity": "93.5", "time": "13:15:17", "@timestamp": "2021-02-06T23:25:23.467Z", "uploader_callsign": "OH3AA_AUTO_RX", "comment": "RS41-SG S1031072 403.000 MHz BT 08:02:46 2.5V", "lat": "60.83970", "time_uploaded": "2021-01-09T13:15:30.183094Z", "lon": "24.24517", "alt": "175", "vel_h": "1.6", "type": "RS41", "frame": "7855", "datetime": "2021-01-09T13:15:30.183094Z", "log_date": "2021-01", "serial": "S1031072", "temp": "-8.5", "@version": "1", "checksum": "F941\\n'", "launch_site": "02963", "launch_site_range_estimate": 342.78539601957056}]