[{"version": "autorx-1.3.2", "humidity": "12.7", "time": "16:51:15", "@timestamp": "2021-02-06T23:23:11.168Z", "uploader_callsign": "DJ0QO", "comment": "RS41-SGP R3310040 402.700 MHz BT 04:57:15 2.9V", "lat": "49.68621", "time_uploaded": "2021-01-10T16:51:00.091081Z", "lon": "7.31448", "alt": "2058", "vel_h": "3.7", "type": "RS41", "frame": "1156", "datetime": "2021-01-10T16:51:00.091081Z", "log_date": "2021-01", "serial": "R3310040", "temp": "-5.6", "@version": "1", "checksum": "82B4\\n'", "launch_site": "10618", "launch_site_range_estimate": 1126.854408619727}, {"version": "autorx-1.4.0", "humidity": "1.2", "time": "18:37:45", "@timestamp": "2021-02-06T23:23:09.101Z", "uploader_callsign": "DK1DB", "comment": "RS41-SGP R3310040 402.700 MHz 4.6hPa BT 03:11:00 2.5V", "lat": "49.22168", "time_uploaded": "2021-01-10T18:37:30.168710Z", "lon": "10.23586", "alt": "35046", "vel_h": "78.5", "type": "RS41", "frame": "7546", "datetime": "2021-01-10T18:37:30.168710Z", "log_date": "2021-01", "serial": "R3310040", "temp": "-30.9", "@version": "1", "checksum": "3F27\\n'", "launch_site": "10618", "launch_site_range_estimate": 1126.854408619727}, {"version": "autorx-1.4.0", "humidity": "12.1", "time": "19:08:57", "@timestamp": "2021-02-06T23:24:01.594Z", "uploader_callsign": "DH1JH-14", "comment": "RS41-SGP R3310040 402.700 MHz 642.0hPa BT 02:39:33 2.5V", "lat": "49.06102", "time_uploaded": "2021-01-10T19:09:00.147095Z", "lon": "10.83948", "alt": "3675", "vel_h": "12.8", "type": "RS41", "frame": "9418", "datetime": "2021-01-10T19:09:00.147095Z", "log_date": "2021-01", "serial": "R3310040", "temp": "-15.1", "@version": "1", "checksum": "D2F8\\n'", "launch_site": "10618", "launch_site_range_estimate": 1126.854408619727}]