[{"version": "autorx-1.4.0", "humidity": "30.6", "time": "23:22:45", "@timestamp": "2021-02-06T23:57:09.422Z", "uploader_callsign": "M6OLZ", "comment": "RS41 S2840441 404.801 MHz 2.9V", "lat": "50.88099", "time_uploaded": "2021-01-09T23:22:30.108989Z", "lon": "0.33469", "alt": "2320", "vel_h": "4.7", "type": "RS41", "frame": "1961", "datetime": "2021-01-09T23:22:30.108989Z", "log_date": "2021-01", "serial": "S2840441", "temp": "-8.3", "@version": "1", "checksum": "3403\\n'", "launch_site": "03882", "launch_site_range_estimate": 1661.6591488561037}, {"version": "autorx-1.4.0", "humidity": "4.4", "time": "00:33:45", "@timestamp": "2021-02-06T23:25:45.364Z", "uploader_callsign": "ONCR16_RX", "comment": "RS41-SG S2840441 404.799 MHz 2.4V", "lat": "50.46735", "time_uploaded": "2021-01-10T00:33:34.744220Z", "lon": "1.03735", "alt": "23964", "vel_h": "52.4", "type": "RS41", "frame": "6221", "datetime": "2021-01-10T00:33:34.744220Z", "log_date": "2021-01", "serial": "S2840441", "temp": "-71.7", "@version": "1", "checksum": "0BEA\\n'", "launch_site": "03882", "launch_site_range_estimate": 1661.6591488561037}, {"version": "autorx-1.4.0", "humidity": "80.4", "time": "01:10:45", "@timestamp": "2021-02-06T23:49:30.120Z", "uploader_callsign": "F5RZC", "comment": "RS41-SG S2840441 404.800 MHz BT 07:54:02 2.7V", "lat": "50.25492", "time_uploaded": "2021-01-10T01:10:30.146594Z", "lon": "1.21631", "alt": "240", "vel_h": "2.5", "type": "RS41", "frame": "8441", "datetime": "2021-01-10T01:10:30.146594Z", "log_date": "2021-01", "serial": "S2840441", "temp": "4.0", "@version": "1", "checksum": "9428\\n'", "launch_site": "03882", "launch_site_range_estimate": 1661.6591488561037}]