[{"version": "autorx-1.4.0", "humidity": "-1.0", "time": "23:39:57", "@timestamp": "2021-02-06T23:50:39.064Z", "uploader_callsign": "TA2GX_AUTO_RX", "comment": "MEISEI IMS100-7018626 403.501 MHz", "lat": "38.39047", "time_uploaded": "2021-01-27T23:40:00.031871Z", "lon": "27.09569", "alt": "2147", "vel_h": "6.4", "type": "IMS100", "frame": "2278", "datetime": "2021-01-27T23:40:00.031871Z", "log_date": "2021-01", "serial": "IMS100-7018626", "temp": "-273.0", "@version": "1", "checksum": "6B1E\\n'", "launch_site": "17220", "launch_site_range_estimate": 1307.6735527403691}, {"version": "autorx-1.4.0", "humidity": "-1.0", "time": "00:29:27", "@timestamp": "2021-02-06T23:50:43.517Z", "uploader_callsign": "TA2GX_AUTO_RX", "comment": "MEISEI IMS100-7018626 403.498 MHz", "lat": "38.46507", "time_uploaded": "2021-01-28T00:29:30.118942Z", "lon": "27.78968", "alt": "18767", "vel_h": "23.0", "type": "IMS100", "frame": "8218", "datetime": "2021-01-28T00:29:30.118942Z", "log_date": "2021-01", "serial": "IMS100-7018626", "temp": "-273.0", "@version": "1", "checksum": "6B8C\\n'", "launch_site": "17220", "launch_site_range_estimate": 1307.6735527403691}, {"version": "autorx-1.4.0", "humidity": "-1.0", "time": "00:29:27", "@timestamp": "2021-02-06T23:50:43.517Z", "uploader_callsign": "TA2GX_AUTO_RX", "comment": "MEISEI IMS100-7018626 403.498 MHz", "lat": "38.46507", "time_uploaded": "2021-01-28T00:29:30.118942Z", "lon": "27.78968", "alt": "18767", "vel_h": "23.0", "type": "IMS100", "frame": "8218", "datetime": "2021-01-28T00:29:30.118942Z", "log_date": "2021-01", "serial": "IMS100-7018626", "temp": "-273.0", "@version": "1", "checksum": "6B8C\\n'", "launch_site": "17220", "launch_site_range_estimate": 1307.6735527403691}]