[{"version": "autorx-1.4.0", "humidity": "-1.0", "time": "11:09:14", "@timestamp": "2021-02-06T23:30:36.268Z", "uploader_callsign": "TRH_RX", "comment": "LMS6 LMS6-8161644 401.015 MHz", "lat": "38.96307", "time_uploaded": "2021-01-14T11:09:00.103807Z", "lon": "-77.47082", "alt": "2236", "vel_h": "9.2", "type": "LMS6-403", "frame": "1593", "datetime": "2021-01-14T11:09:00.103807Z", "log_date": "2021-01", "serial": "LMS6-8161644", "temp": "-273.0", "@version": "1", "checksum": "704D\\n'", "launch_site": "72403", "launch_site_range_estimate": 1991.6353482332306}, {"version": "autorx-1.4.0", "humidity": "-1.0", "time": "12:43:14", "@timestamp": "2021-02-06T23:30:34.060Z", "uploader_callsign": "TRH_RX", "comment": "LMS6 LMS6-8161644 401.014 MHz", "lat": "38.75745", "time_uploaded": "2021-01-14T12:43:00.043007Z", "lon": "-76.53249", "alt": "31565", "vel_h": "18.9", "type": "LMS6-403", "frame": "7233", "datetime": "2021-01-14T12:43:00.043007Z", "log_date": "2021-01", "serial": "LMS6-8161644", "temp": "-273.0", "@version": "1", "checksum": "FEF9\\n'", "launch_site": "72403", "launch_site_range_estimate": 1991.6353482332306}, {"version": "autorx-1.4.0", "humidity": "-1.0", "time": "14:23:44", "@timestamp": "2021-02-06T23:29:39.833Z", "uploader_callsign": "TRH_RX", "comment": "LMS6 LMS6-8161644 401.015 MHz", "lat": "38.72757", "time_uploaded": "2021-01-14T14:23:30.170066Z", "lon": "-75.54877", "alt": "365", "vel_h": "3.1", "type": "LMS6-403", "frame": "13263", "datetime": "2021-01-14T14:23:30.170066Z", "log_date": "2021-01", "serial": "LMS6-8161644", "temp": "-273.0", "@version": "1", "checksum": "D7E5\\n'", "launch_site": "72403", "launch_site_range_estimate": 1991.6353482332306}]