[{"version": "autorx-1.4.0", "humidity": "1.7", "time": "12:54:45", "@timestamp": "2021-02-06T23:44:29.768Z", "uploader_callsign": "G7GQW_AUTO_RX", "comment": "RS41 S3110495 405.301 MHz 2.5V", "lat": "51.55319", "time_uploaded": "2021-01-14T12:54:30.086086Z", "lon": "-8.10010", "alt": "29344", "vel_h": "59.6", "type": "payload_telemetry", "frame": "7169", "datetime": "2021-01-14T12:54:30.086086Z", "log_date": "2021-01", "serial": "S3110495", "temp": "-58.7", "@version": "1", "checksum": "745E\\n'"}, {"version": "autorx-1.4.0", "humidity": "2.1", "time": "13:01:15", "@timestamp": "2021-02-06T23:45:31.854Z", "uploader_callsign": "G7GQW_AUTO_RX", "comment": "RS41-SG S3110495 405.301 MHz 2.6V", "lat": "51.54231", "time_uploaded": "2021-01-14T13:01:00.077415Z", "lon": "-7.75842", "alt": "32065", "vel_h": "59.4", "type": "payload_telemetry", "frame": "7559", "datetime": "2021-01-14T13:01:00.077415Z", "log_date": "2021-01", "serial": "S3110495", "temp": "-44.0", "@version": "1", "checksum": "FF81\\n'"}, {"version": "autorx-1.4.0", "humidity": "2.0", "time": "13:02:15", "@timestamp": "2021-02-07T00:00:14.932Z", "uploader_callsign": "G7GQW_AUTO_RX", "comment": "RS41-SG S3110495 405.301 MHz 2.6V", "lat": "51.54761", "time_uploaded": "2021-01-14T13:02:00.061920Z", "lon": "-7.70508", "alt": "32055", "vel_h": "61.9", "type": "payload_telemetry", "frame": "7619", "datetime": "2021-01-14T13:02:00.061920Z", "log_date": "2021-01", "serial": "S3110495", "temp": "-43.4", "@version": "1", "checksum": "51DA\\n'"}]