[{"version": "autorx-1.3.2", "humidity": "98.8", "time": "11:34:15", "@timestamp": "2021-02-06T16:35:27.350Z", "uploader_callsign": "ON4CBN-Rpi2", "comment": "RS41-SGP-Ozone R3341035 403.501 MHz 2.8V", "lat": "50.78997", "time_uploaded": "2021-01-08T11:34:00.162053Z", "lon": "4.37396", "alt": "1141", "vel_h": "9.5", "type": "RS41", "frame": "1613", "datetime": "2021-01-08T11:34:00.162053Z", "log_date": "2021-01", "serial": "R3341035", "temp": "-3.7", "@version": "1", "checksum": "5DB8\\n'", "launch_site": "06447", "launch_site_range_estimate": 1353.8960339258806}, {"version": "autorx-1.4.0", "humidity": "1.4", "time": "13:08:05", "@timestamp": "2021-02-06T16:40:58.012Z", "uploader_callsign": "PE1PSI_AUTO_RX", "comment": "RS41-SGP-Ozone R3341035 403.501 MHz 9.8hPa 2.6V", "lat": "50.68680", "time_uploaded": "2021-01-08T13:08:00.043537Z", "lon": "6.11111", "alt": "29620", "vel_h": "53.6", "type": "RS41", "frame": "7243", "datetime": "2021-01-08T13:08:00.043537Z", "log_date": "2021-01", "serial": "R3341035", "temp": "-60.9", "@version": "1", "checksum": "A101\\n'", "launch_site": "06447", "launch_site_range_estimate": 1353.8960339258806}, {"version": "autorx-1.4.0", "humidity": "98.7", "time": "13:53:09", "@timestamp": "2021-02-06T16:36:12.820Z", "uploader_callsign": "DK1DB", "comment": "RS41-SGP-Ozone R3341035 403.500 MHz 957.2hPa BT 07:45:28 2.5V", "lat": "50.56131", "time_uploaded": "2021-01-08T13:53:00.107193Z", "lon": "6.65352", "alt": "518", "vel_h": "1.2", "type": "RS41", "frame": "9947", "datetime": "2021-01-08T13:53:00.107193Z", "log_date": "2021-01", "serial": "R3341035", "temp": "-0.8", "@version": "1", "checksum": "1391\\n'", "launch_site": "06447", "launch_site_range_estimate": 1353.8960339258806}]