[{"version": "autorx-1.4.0", "humidity": "-1.0", "time": "10:19:27", "@timestamp": "2021-02-06T23:24:42.846Z", "uploader_callsign": "OZ1ARQ_AUTO_RX", "comment": "RS41-SG R4220846 405.301 MHz 2.8V", "lat": "54.03021", "time_uploaded": "2021-01-08T10:19:21.128704Z", "lon": "11.79218", "alt": "10100", "vel_h": "3.4", "type": "payload_telemetry", "frame": "3272", "datetime": "2021-01-08T10:19:21.128704Z", "log_date": "2021-01", "serial": "R4220846", "temp": "-57.0", "@version": "1", "checksum": "E6A5\\n'"}, {"version": "autorx-1.4.0", "humidity": "4.3", "time": "10:59:15", "@timestamp": "2021-02-06T23:23:18.694Z", "uploader_callsign": "OZ1ARQ_AUTO_RX", "comment": "RS41-SG R4220846 405.301 MHz 2.6V", "lat": "54.07051", "time_uploaded": "2021-01-08T10:59:00.090319Z", "lon": "12.41397", "alt": "19514", "vel_h": "28.0", "type": "payload_telemetry", "frame": "5660", "datetime": "2021-01-08T10:59:00.090319Z", "log_date": "2021-01", "serial": "R4220846", "temp": "-68.4", "@version": "1", "checksum": "C657\\n'"}, {"version": "autorx-1.4.0", "humidity": "-1.0", "time": "11:12:51", "@timestamp": "2021-02-06T23:25:34.234Z", "uploader_callsign": "OZ6F", "comment": "RS41 R4220846 405.300 MHz 2.6V", "lat": "54.09442", "time_uploaded": "2021-01-08T11:13:00.043171Z", "lon": "12.77050", "alt": "16192", "vel_h": "25.1", "type": "payload_telemetry", "frame": "6476", "datetime": "2021-01-08T11:13:00.043171Z", "log_date": "2021-01", "serial": "R4220846", "temp": "-273.0", "@version": "1", "checksum": "659E\\n'"}]