[{"version": "autorx-1.3.2", "humidity": "-1.0", "time": "11:32:15", "@timestamp": "2021-02-06T23:49:57.337Z", "uploader_callsign": "PY3JRT", "comment": "RS41 S0830134 403.002 MHz 3.0V", "lat": "-29.99886", "time_uploaded": "2021-01-13T11:32:00.127552Z", "lon": "-51.18910", "alt": "504", "vel_h": "8.1", "type": "RS41", "frame": "2312", "datetime": "2021-01-13T11:32:00.127552Z", "log_date": "2021-01", "serial": "S0830134", "temp": "-273.0", "@version": "1", "checksum": "A005\\n'", "launch_site": "83971", "launch_site_range_estimate": 572.1909363086257}, {"version": "autorx-1.3.0", "humidity": "1.6", "time": "12:27:15", "@timestamp": "2021-02-06T23:59:08.014Z", "uploader_callsign": "PU3XGS", "comment": "RS41-SGP S0830134 403.000 MHz", "lat": "-29.99816", "time_uploaded": "2021-01-13T12:27:00.034513Z", "lon": "-50.90051", "alt": "23019", "vel_h": "9.3", "type": "RS41", "frame": "5612", "datetime": "2021-01-13T12:27:00.034513Z", "log_date": "2021-01", "serial": "S0830134", "temp": "-59.6", "@version": "1", "checksum": "2A76\\n'", "launch_site": "83971", "launch_site_range_estimate": 572.1909363086257}, {"version": "autorx-1.3.0", "humidity": "90.4", "time": "12:59:25", "@timestamp": "2021-02-06T23:30:23.500Z", "uploader_callsign": "PU3XGS", "comment": "RS41-SGP S0830134 403.000 MHz BT 07:58:35", "lat": "-29.99953", "time_uploaded": "2021-01-13T12:59:30.181084Z", "lon": "-50.67493", "alt": "1099", "vel_h": "5.3", "type": "RS41", "frame": "7542", "datetime": "2021-01-13T12:59:30.181084Z", "log_date": "2021-01", "serial": "S0830134", "temp": "14.1", "@version": "1", "checksum": "2CDB\\n'", "launch_site": "83971", "launch_site_range_estimate": 572.1909363086257}]