[{"version": "autorx-1.3.0", "humidity": "-1.0", "time": "11:34:42", "@timestamp": "2021-02-07T00:01:11.421Z", "uploader_callsign": "W5CDT@yahoo.com", "comment": "RS41 S3250598 404.301 MHz", "lat": "29.26252", "time_uploaded": "2021-01-04T11:34:29.353363Z", "lon": "-100.64743", "alt": "8999", "vel_h": "21.8", "type": "payload_telemetry", "frame": "3292", "datetime": "2021-01-04T11:34:29.353363Z", "log_date": "2021-01", "serial": "S3250598", "temp": "-273.0", "@version": "1", "checksum": "4FAB\\n'"}, {"version": "autorx-1.4.0", "humidity": "1.9", "time": "13:02:15", "@timestamp": "2021-02-06T23:56:12.139Z", "uploader_callsign": "KV5TX", "comment": "RS41-SGP S3250598 404.301 MHz 4.5hPa 2.5V", "lat": "29.26295", "time_uploaded": "2021-01-04T13:02:00.142576Z", "lon": "-99.88812", "alt": "35868", "vel_h": "8.6", "type": "payload_telemetry", "frame": "8545", "datetime": "2021-01-04T13:02:00.142576Z", "log_date": "2021-01", "serial": "S3250598", "temp": "-44.9", "@version": "1", "checksum": "212A\\n'"}, {"version": "autorx-1.3.0", "humidity": "22.5", "time": "13:14:02", "@timestamp": "2021-02-06T23:44:11.017Z", "uploader_callsign": "W5CDT@yahoo.com", "comment": "RS41-SGP S3250598 404.301 MHz BT 08:19:41", "lat": "29.23997", "time_uploaded": "2021-01-04T13:14:00.069016Z", "lon": "-99.77034", "alt": "5407", "vel_h": "18.5", "type": "payload_telemetry", "frame": "9252", "datetime": "2021-01-04T13:14:00.069016Z", "log_date": "2021-01", "serial": "S3250598", "temp": "-8.5", "@version": "1", "checksum": "CA65\\n'"}]