[{"version": "autorx-1.3.2", "humidity": "-1.0", "time": "11:49:15", "@timestamp": "2021-02-06T23:50:14.633Z", "uploader_callsign": "PU2MST", "comment": "RS41-SGP S0630773 405.292 MHz 2.9V", "lat": "-23.52105", "time_uploaded": "2021-01-11T11:49:00.136510Z", "lon": "-46.65343", "alt": "7132", "vel_h": "11.6", "type": "payload_telemetry", "frame": "2065", "datetime": "2021-01-11T11:49:00.136510Z", "log_date": "2021-01", "serial": "S0630773", "temp": "-273.0", "@version": "1", "checksum": "249A\\n'"}, {"version": "autorx-1.4.0", "humidity": "2.3", "time": "12:25:45", "@timestamp": "2021-02-06T23:22:51.564Z", "uploader_callsign": "PU2SDM", "comment": "RS41-SGP S0630773 405.273 MHz 25.8hPa 2.6V", "lat": "-23.47068", "time_uploaded": "2021-01-11T12:25:30.161756Z", "lon": "-46.70236", "alt": "24831", "vel_h": "16.3", "type": "payload_telemetry", "frame": "4255", "datetime": "2021-01-11T12:25:30.161756Z", "log_date": "2021-01", "serial": "S0630773", "temp": "-56.0", "@version": "1", "checksum": "B7D2\\n'"}, {"version": "autorx-1.3.2", "humidity": "85.2", "time": "13:37:41", "@timestamp": "2021-02-06T23:24:35.765Z", "uploader_callsign": "PU2MST", "comment": "RS41-SGP S0630773 405.292 MHz BT 07:18:36 2.8V", "lat": "-23.37051", "time_uploaded": "2021-01-11T13:37:30.120148Z", "lon": "-46.71380", "alt": "3356", "vel_h": "5.5", "type": "payload_telemetry", "frame": "8571", "datetime": "2021-01-11T13:37:30.120148Z", "log_date": "2021-01", "serial": "S0630773", "temp": "9.4", "@version": "1", "checksum": "5804\\n'"}]