[{"version": "autorx-1.4.0", "humidity": "-1.0", "time": "13:15:28", "@timestamp": "2021-02-06T23:56:45.176Z", "uploader_callsign": "IZ1GRJ-15", "comment": "DFM09 DFM-18049978 405.009 MHz 5.1V", "lat": "42.44359", "time_uploaded": "2021-01-26T13:15:30.145631Z", "lon": "6.87011", "alt": "10984", "vel_h": "50.9", "type": "payload_telemetry", "frame": "1295702128", "datetime": "2021-01-26T13:15:30.145631Z", "log_date": "2021-01", "serial": "DFM-18049978", "temp": "-57.9", "@version": "1", "checksum": "92B3\\n'"}, {"version": "autorx-1.4.0", "humidity": "-1.0", "time": "13:32:28", "@timestamp": "2021-02-06T23:56:35.425Z", "uploader_callsign": "IZ1GRJ-15", "comment": "DFM09 DFM-18049978 405.008 MHz 4.7V", "lat": "42.15107", "time_uploaded": "2021-01-26T13:32:30.071523Z", "lon": "7.16077", "alt": "15400", "vel_h": "34.3", "type": "payload_telemetry", "frame": "1295703148", "datetime": "2021-01-26T13:32:30.071523Z", "log_date": "2021-01", "serial": "DFM-18049978", "temp": "-60.2", "@version": "1", "checksum": "0ACA\\n'"}, {"version": "autorx-1.4.0", "humidity": "-1.0", "time": "13:37:28", "@timestamp": "2021-02-06T23:56:35.656Z", "uploader_callsign": "IZ1GRJ-15", "comment": "DFM09 DFM-18049978 405.007 MHz 4.7V", "lat": "42.06062", "time_uploaded": "2021-01-26T13:37:30.101551Z", "lon": "7.24662", "alt": "10231", "vel_h": "53.3", "type": "payload_telemetry", "frame": "1295703448", "datetime": "2021-01-26T13:37:30.101551Z", "log_date": "2021-01", "serial": "DFM-18049978", "temp": "-57.4", "@version": "1", "checksum": "3579\\n'"}]