[{"version": "autorx-1.4.0", "humidity": "-1.0", "time": "11:14:44", "@timestamp": "2021-02-06T23:59:00.339Z", "uploader_callsign": "TRH_RX3", "comment": "LMS6 LMS6-8158896 402.510 MHz", "lat": "22.00347", "time_uploaded": "2021-01-26T11:14:30.106356Z", "lon": "-159.39768", "alt": "3298", "vel_h": "8.5", "type": "LMS6-403", "frame": "1239", "datetime": "2021-01-26T11:14:30.106356Z", "log_date": "2021-01", "serial": "LMS6-8158896", "temp": "-273.0", "@version": "1", "checksum": "3163\\n'", "launch_site": "91165", "launch_site_range_estimate": 5371.186351872147}, {"version": "autorx-1.4.0", "humidity": "-1.0", "time": "12:35:14", "@timestamp": "2021-02-06T23:58:55.934Z", "uploader_callsign": "TRH_RX3", "comment": "LMS6 LMS6-8158896 402.501 MHz", "lat": "22.00795", "time_uploaded": "2021-01-26T12:35:00.117771Z", "lon": "-159.29535", "alt": "24029", "vel_h": "7.9", "type": "LMS6-403", "frame": "6069", "datetime": "2021-01-26T12:35:00.117771Z", "log_date": "2021-01", "serial": "LMS6-8158896", "temp": "-273.0", "@version": "1", "checksum": "D394\\n'", "launch_site": "91165", "launch_site_range_estimate": 5371.186351872147}, {"version": "autorx-1.4.0", "humidity": "-1.0", "time": "13:08:55", "@timestamp": "2021-02-06T23:58:57.580Z", "uploader_callsign": "TRH_RX3", "comment": "LMS6 LMS6-8158896 402.509 MHz", "lat": "22.02098", "time_uploaded": "2021-01-26T13:09:00.082636Z", "lon": "-159.28992", "alt": "2927", "vel_h": "9.4", "type": "LMS6-403", "frame": "8090", "datetime": "2021-01-26T13:09:00.082636Z", "log_date": "2021-01", "serial": "LMS6-8158896", "temp": "-273.0", "@version": "1", "checksum": "EC53\\n'", "launch_site": "91165", "launch_site_range_estimate": 5371.186351872147}]