[{"version": "autorx-1.4.0", "humidity": "-1.0", "time": "11:20:23", "@timestamp": "2021-02-06T23:59:00.988Z", "uploader_callsign": "KC2PIT", "comment": "MK2LMS LMS6-7398885 1680.000 MHz", "lat": "42.94266", "time_uploaded": "2021-01-26T11:20:07.837375Z", "lon": "-78.73565", "alt": "743", "vel_h": "10.0", "type": "LMS6-1680", "frame": "2379", "datetime": "2021-01-26T11:20:07.837375Z", "log_date": "2021-01", "serial": "LMS6-7398885", "temp": "-273.0", "@version": "1", "checksum": "FF58\\n'", "launch_site": "72528", "launch_site_range_estimate": 1373.132853244273}, {"version": "autorx-1.4.0", "humidity": "-1.0", "time": "13:00:43", "@timestamp": "2021-02-06T23:58:57.574Z", "uploader_callsign": "KD2EAT", "comment": "MK2LMS LMS6-7398885 1680.000 MHz", "lat": "42.81750", "time_uploaded": "2021-01-26T13:00:30.092927Z", "lon": "-77.04903", "alt": "32958", "vel_h": "12.1", "type": "LMS6-1680", "frame": "8399", "datetime": "2021-01-26T13:00:30.092927Z", "log_date": "2021-01", "serial": "LMS6-7398885", "temp": "-273.0", "@version": "1", "checksum": "B72A\\n'", "launch_site": "72528", "launch_site_range_estimate": 1373.132853244273}, {"version": "autorx-1.4.0", "humidity": "-1.0", "time": "13:32:43", "@timestamp": "2021-02-06T23:59:10.955Z", "uploader_callsign": "KD2EAT", "comment": "MK2LMS LMS6-7398885 1680.000 MHz", "lat": "42.72565", "time_uploaded": "2021-01-26T13:32:30.140676Z", "lon": "-76.29391", "alt": "8770", "vel_h": "68.0", "type": "LMS6-1680", "frame": "10319", "datetime": "2021-01-26T13:32:30.140676Z", "log_date": "2021-01", "serial": "LMS6-7398885", "temp": "-273.0", "@version": "1", "checksum": "908C\\n'", "launch_site": "72528", "launch_site_range_estimate": 1373.132853244273}]