[{"version": "autorx-1.4.0", "humidity": "-1.0", "time": "00:10:15", "@timestamp": "2021-02-06T23:43:52.455Z", "uploader_callsign": "PY1TCM", "comment": "RS41 R4010133 405.302 MHz 2.7V", "lat": "-22.78606", "time_uploaded": "2021-01-19T00:10:00.113079Z", "lon": "-43.40267", "alt": "13827", "vel_h": "23.9", "type": "payload_telemetry", "frame": "4122", "datetime": "2021-01-19T00:10:00.113079Z", "log_date": "2021-01", "serial": "R4010133", "temp": "-273.0", "@version": "1", "checksum": "1296\\n'"}, {"version": "autorx-1.4.0", "humidity": "2.2", "time": "00:36:45", "@timestamp": "2021-02-06T23:43:55.534Z", "uploader_callsign": "PY1TCM", "comment": "RS41-SGP R4010133 405.302 MHz 30.4hPa 2.7V", "lat": "-22.73326", "time_uploaded": "2021-01-19T00:36:30.011795Z", "lon": "-43.60348", "alt": "23728", "vel_h": "15.6", "type": "payload_telemetry", "frame": "5712", "datetime": "2021-01-19T00:36:30.011795Z", "log_date": "2021-01", "serial": "R4010133", "temp": "-58.8", "@version": "1", "checksum": "F34D\\n'"}, {"version": "autorx-1.4.0", "humidity": "57.0", "time": "02:12:40", "@timestamp": "2021-02-06T23:46:11.707Z", "uploader_callsign": "PY1TCM", "comment": "RS41-SGP R4010133 405.302 MHz 903.7hPa BT 06:56:43 2.9V", "lat": "-22.72356", "time_uploaded": "2021-01-19T02:12:30.187610Z", "lon": "-43.99093", "alt": "976", "vel_h": "4.8", "type": "payload_telemetry", "frame": "11467", "datetime": "2021-01-19T02:12:30.187610Z", "log_date": "2021-01", "serial": "R4010133", "temp": "24.0", "@version": "1", "checksum": "291A\\n'"}]