[{"version": "autorx-1.4.0", "humidity": "-1.0", "time": "10:48:50", "@timestamp": "2021-02-06T23:57:27.417Z", "uploader_callsign": "DK1DB", "comment": "RS41 S0410565 405.300 MHz 2.9V", "lat": "51.42340", "time_uploaded": "2021-01-19T10:48:34.219528Z", "lon": "7.02733", "alt": "1057", "vel_h": "29.1", "type": "RS41", "frame": "1607", "datetime": "2021-01-19T10:48:34.219528Z", "log_date": "2021-01", "serial": "S0410565", "temp": "-273.0", "@version": "1", "checksum": "9E44\\n'", "launch_site": "10410", "launch_site_range_estimate": 4524.102685839364}, {"version": "autorx-1.4.0", "humidity": "2.1", "time": "12:30:45", "@timestamp": "2021-02-06T23:57:22.242Z", "uploader_callsign": "KS_AUTO_RX", "comment": "RS41-SGP S0410565 405.300 MHz 7.7hPa 2.6V", "lat": "51.15202", "time_uploaded": "2021-01-19T12:30:33.547102Z", "lon": "9.98031", "alt": "31441", "vel_h": "76.0", "type": "RS41", "frame": "7722", "datetime": "2021-01-19T12:30:33.547102Z", "log_date": "2021-01", "serial": "S0410565", "temp": "-38.0", "@version": "1", "checksum": "C6D2\\n'", "launch_site": "10410", "launch_site_range_estimate": 4524.102685839364}, {"version": "autorx-1.4.0", "humidity": "92.7", "time": "13:14:15", "@timestamp": "2021-02-06T23:54:49.891Z", "uploader_callsign": "DL1ZP-14", "comment": "RS41-SGP S0410565 405.301 MHz 664.2hPa BT 07:47:38 2.5V", "lat": "50.91179", "time_uploaded": "2021-01-19T13:14:00.120778Z", "lon": "11.12908", "alt": "3357", "vel_h": "24.9", "type": "RS41", "frame": "10332", "datetime": "2021-01-19T13:14:00.120778Z", "log_date": "2021-01", "serial": "S0410565", "temp": "-8.8", "@version": "1", "checksum": "4A58\\n'", "launch_site": "10410", "launch_site_range_estimate": 4524.102685839364}]