[{"version": "autorx-1.4.0", "humidity": "90.5", "time": "11:01:58", "@timestamp": "2021-02-06T23:58:24.974Z", "uploader_callsign": "OZ1ARQ", "comment": "RS41-SGP S1440867 402.300 MHz 567.5hPa 2.8V", "lat": "54.16403", "time_uploaded": "2021-01-19T11:01:43.048964Z", "lon": "13.56492", "alt": "4459", "vel_h": "20.6", "type": "RS41", "frame": "2537", "datetime": "2021-01-19T11:01:43.048964Z", "log_date": "2021-01", "serial": "S1440867", "temp": "-19.6", "@version": "1", "checksum": "93EB\\n'", "launch_site": "10184", "launch_site_range_estimate": 12614.529885944004}, {"version": "autorx-1.4.0", "humidity": "7.0", "time": "11:58:44", "@timestamp": "2021-02-06T23:57:19.622Z", "uploader_callsign": "OZ1SKY_AUTO_RX", "comment": "RS41-SGP S1440867 402.300 MHz 37.6hPa 2.6V", "lat": "53.75431", "time_uploaded": "2021-01-19T11:58:34.233893Z", "lon": "14.80579", "alt": "21272", "vel_h": "13.9", "type": "RS41", "frame": "5943", "datetime": "2021-01-19T11:58:34.233893Z", "log_date": "2021-01", "serial": "S1440867", "temp": "-72.8", "@version": "1", "checksum": "8A7A\\n'", "launch_site": "10184", "launch_site_range_estimate": 12614.529885944004}, {"version": "autorx-1.4.0", "humidity": "-1.0", "time": "12:29:18", "@timestamp": "2021-02-06T23:57:22.172Z", "uploader_callsign": "CHANGEME_AUTO_RX", "comment": "RS41 S1440867 402.300 MHz 2.4V", "lat": "53.52214", "time_uploaded": "2021-01-19T12:29:30.090908Z", "lon": "15.37381", "alt": "9158", "vel_h": "53.2", "type": "RS41", "frame": "7777", "datetime": "2021-01-19T12:29:30.090908Z", "log_date": "2021-01", "serial": "S1440867", "temp": "-273.0", "@version": "1", "checksum": "FECC\\n'", "launch_site": "10184", "launch_site_range_estimate": 12614.529885944004}]