[{"version": "autorx-1.4.0", "humidity": "-1.0", "time": "00:00:46", "@timestamp": "2021-02-07T00:01:48.671Z", "uploader_callsign": "TRH_RX", "comment": "LMS6 LMS6-8159848 404.008 MHz", "lat": "37.87283", "time_uploaded": "2021-01-18T00:00:31.032357Z", "lon": "-79.02259", "alt": "17161", "vel_h": "26.4", "type": "payload_telemetry", "frame": "3803", "datetime": "2021-01-18T00:00:31.032357Z", "log_date": "2021-01", "serial": "LMS6-8159848", "temp": "-273.0", "@version": "1", "checksum": "8451\\n'"}, {"version": "autorx-1.4.0", "humidity": "-1.0", "time": "00:49:57", "@timestamp": "2021-02-06T23:32:08.805Z", "uploader_callsign": "TRH_RX", "comment": "LMS6 LMS6-8159848 404.007 MHz", "lat": "37.76786", "time_uploaded": "2021-01-18T00:50:03.328789Z", "lon": "-78.87128", "alt": "33262", "vel_h": "7.9", "type": "payload_telemetry", "frame": "6754", "datetime": "2021-01-18T00:50:03.328789Z", "log_date": "2021-01", "serial": "LMS6-8159848", "temp": "-273.0", "@version": "1", "checksum": "38A0\\n'"}, {"version": "autorx-1.4.0", "humidity": "-1.0", "time": "02:17:22", "@timestamp": "2021-02-06T23:32:11.064Z", "uploader_callsign": "TRH_RX", "comment": "LMS6 LMS6-8159848 404.011 MHz", "lat": "38.62253", "time_uploaded": "2021-01-18T02:17:30.151961Z", "lon": "-77.04198", "alt": "1035", "vel_h": "16.1", "type": "payload_telemetry", "frame": "11999", "datetime": "2021-01-18T02:17:30.151961Z", "log_date": "2021-01", "serial": "LMS6-8159848", "temp": "-273.0", "@version": "1", "checksum": "C464\\n'"}]