[{"version": "autorx-1.3.1", "humidity": "71.6", "time": "11:17:11", "@timestamp": "2021-02-06T23:55:41.965Z", "uploader_callsign": "HB9HFD", "comment": "RS41-Ozone R3710903 404.500 MHz", "lat": "46.70286", "time_uploaded": "2021-01-27T11:17:00.174973Z", "lon": "7.15389", "alt": "6137", "vel_h": "36.6", "type": "payload_telemetry", "frame": "3432", "datetime": "2021-01-27T11:17:00.174973Z", "log_date": "2021-01", "serial": "R3710903", "temp": "-28.9", "@version": "1", "checksum": "DBF1\\n'"}, {"version": "autorx-1.4.0", "humidity": "1.9", "time": "12:43:15", "@timestamp": "2021-02-06T23:56:14.425Z", "uploader_callsign": "FRS2013", "comment": "RS41-SG-Ozone R3710903 404.500 MHz 2.6V", "lat": "45.37990", "time_uploaded": "2021-01-27T12:43:00.168961Z", "lon": "7.75801", "alt": "33019", "vel_h": "26.8", "type": "payload_telemetry", "frame": "8596", "datetime": "2021-01-27T12:43:00.168961Z", "log_date": "2021-01", "serial": "R3710903", "temp": "-47.2", "@version": "1", "checksum": "8EE2\\n'"}, {"version": "autorx-1.4.0", "humidity": "85.9", "time": "13:47:45", "@timestamp": "2021-02-06T23:56:51.626Z", "uploader_callsign": "IW1CGW-15", "comment": "RS41-SG-Ozone R3710903 404.500 MHz BT 07:32:42 2.7V", "lat": "44.39474", "time_uploaded": "2021-01-27T13:47:30.088352Z", "lon": "8.33582", "alt": "1354", "vel_h": "5.5", "type": "payload_telemetry", "frame": "12466", "datetime": "2021-01-27T13:47:30.088352Z", "log_date": "2021-01", "serial": "R3710903", "temp": "-1.0", "@version": "1", "checksum": "4547\\n'"}]