[{"version": "autorx-1.4.0", "humidity": "-1.0", "time": "23:07:14", "@timestamp": "2021-02-06T23:50:55.198Z", "uploader_callsign": "KL1EL", "comment": "RS41-SGP S3540128 405.300 MHz 2.8V", "lat": "61.16531", "time_uploaded": "2021-01-27T23:07:00.179720Z", "lon": "-149.99036", "alt": "1240", "vel_h": "4.1", "type": "RS41", "frame": "1921", "datetime": "2021-01-27T23:07:00.179720Z", "log_date": "2021-01", "serial": "S3540128", "temp": "-273.0", "@version": "1", "checksum": "CB7D\\n'", "launch_site": "70273", "launch_site_range_estimate": 979.7356422576131}, {"version": "autorx-1.4.0", "humidity": "54.7", "time": "23:25:09", "@timestamp": "2021-02-06T23:50:56.403Z", "uploader_callsign": "KL1EL", "comment": "RS41-SGP S3540128 405.300 MHz 379.0hPa 2.7V", "lat": "61.15668", "time_uploaded": "2021-01-27T23:25:00.113516Z", "lon": "-149.71442", "alt": "7387", "vel_h": "34.0", "type": "RS41", "frame": "2996", "datetime": "2021-01-27T23:25:00.113516Z", "log_date": "2021-01", "serial": "S3540128", "temp": "-34.8", "@version": "1", "checksum": "DE9F\\n'", "launch_site": "70273", "launch_site_range_estimate": 979.7356422576131}, {"version": "autorx-1.4.0", "humidity": "54.7", "time": "23:25:09", "@timestamp": "2021-02-06T23:50:56.403Z", "uploader_callsign": "KL1EL", "comment": "RS41-SGP S3540128 405.300 MHz 379.0hPa 2.7V", "lat": "61.15668", "time_uploaded": "2021-01-27T23:25:00.113516Z", "lon": "-149.71442", "alt": "7387", "vel_h": "34.0", "type": "RS41", "frame": "2996", "datetime": "2021-01-27T23:25:00.113516Z", "log_date": "2021-01", "serial": "S3540128", "temp": "-34.8", "@version": "1", "checksum": "DE9F\\n'", "launch_site": "70273", "launch_site_range_estimate": 979.7356422576131}]