[{"version": "autorx-1.4.0", "humidity": "-1.0", "time": "04:48:15", "@timestamp": "2021-02-06T20:08:48.380Z", "uploader_callsign": "DK1DB", "comment": "RS41 S2310971 405.300 MHz 2.9V", "lat": "51.39467", "time_uploaded": "2021-01-03T04:48:00.047301Z", "lon": "6.94629", "alt": "1077", "vel_h": "15.5", "type": "RS41", "frame": "1690", "datetime": "2021-01-03T04:48:00.047301Z", "log_date": "2021-01", "serial": "S2310971", "temp": "-4.8", "@version": "1", "checksum": "A3F7\\n'", "launch_site": "10410", "launch_site_range_estimate": 1965.988527934674}, {"version": "autorx-1.4.0", "humidity": "1.5", "time": "06:25:45", "@timestamp": "2021-02-06T20:09:04.270Z", "uploader_callsign": "DK1DB", "comment": "RS41-SGP S2310971 405.300 MHz 8.2hPa 2.5V", "lat": "51.13943", "time_uploaded": "2021-01-03T06:25:30.185835Z", "lon": "8.13379", "alt": "31132", "vel_h": "62.3", "type": "RS41", "frame": "7540", "datetime": "2021-01-03T06:25:30.185835Z", "log_date": "2021-01", "serial": "S2310971", "temp": "-52.2", "@version": "1", "checksum": "B83C\\n'", "launch_site": "10410", "launch_site_range_estimate": 1965.988527934674}, {"version": "autorx-1.4.0", "humidity": "64.5", "time": "06:57:56", "@timestamp": "2021-02-06T23:53:00.524Z", "uploader_callsign": "DK1DB", "comment": "RS41-SGP S2310971 405.300 MHz 794.8hPa BT 07:59:06 2.6V", "lat": "51.07179", "time_uploaded": "2021-01-03T06:58:00.174601Z", "lon": "8.38579", "alt": "1974", "vel_h": "13.0", "type": "RS41", "frame": "9471", "datetime": "2021-01-03T06:58:00.174601Z", "log_date": "2021-01", "serial": "S2310971", "temp": "-4.8", "@version": "1", "checksum": "1608\\n'", "launch_site": "10410", "launch_site_range_estimate": 1965.988527934674}]