[{"version": "autorx-1.2.3", "humidity": "-1.0", "time": "11:23:50", "@timestamp": "2021-02-06T12:49:52.306Z", "uploader_callsign": "PE1MJA_AUTO_RX", "comment": "RS41 R4051288 403.901 MHz", "lat": "52.09699", "time_uploaded": "2020-03-21T11:23:40.837039Z", "lon": "5.14337", "alt": "846", "vel_h": "13.0", "type": "RS41", "frame": "2377", "datetime": "2020-03-21T11:23:40.837039Z", "log_date": "2020-03", "serial": "R4051288", "temp": "-273.0", "@version": "1", "checksum": "59A7\\n'", "launch_site": "06260", "launch_site_range_estimate": 2488.360635883927}, {"version": "autorx-1.2.3", "humidity": "0.5", "time": "12:47:23", "@timestamp": "2021-02-06T12:42:37.095Z", "uploader_callsign": "PD4C_AUTO_RX", "comment": "RS41-SGP R4051288 403.900 MHz", "lat": "52.02867", "time_uploaded": "2020-03-21T12:47:05.134780Z", "lon": "5.33601", "alt": "28459", "vel_h": "3.1", "type": "RS41", "frame": "7390", "datetime": "2020-03-21T12:47:05.134780Z", "log_date": "2020-03", "serial": "R4051288", "temp": "-49.6", "@version": "1", "checksum": "2D35\\n'", "launch_site": "06260", "launch_site_range_estimate": 2488.360635883927}, {"version": "autorx-1.2.3", "humidity": "60.4", "time": "13:51:32", "@timestamp": "2021-02-06T12:42:40.012Z", "uploader_callsign": "PE1MJA_AUTO_RX", "comment": "RS41-SGP R4051288 403.901 MHz BT 07:26:38", "lat": "51.94105", "time_uploaded": "2020-03-21T13:51:30.186103Z", "lon": "5.14183", "alt": "395", "vel_h": "13.7", "type": "RS41", "frame": "11239", "datetime": "2020-03-21T13:51:30.186103Z", "log_date": "2020-03", "serial": "R4051288", "temp": "4.3", "@version": "1", "checksum": "21E2\\n'", "launch_site": "06260", "launch_site_range_estimate": 2488.360635883927}]