[{"software_name": "radiosonde_auto_rx", "software_version": "1.5.6", "uploader_callsign": "PE1MIU-11", "uploader_position": "51.76,5.53", "uploader_antenna": "1/4 wave monopole", "time_received": "2021-09-27T23:32:44.303860Z", "datetime": "2021-09-27T23:33:00.000000Z", "manufacturer": "Vaisala", "type": "RS41", "serial": "S1230514", "subtype": "RS41", "frame": 827, "lat": 52.10434, "lon": 5.19702, "alt": 1017.78774, "vel_v": 4.09905, "vel_h": 8.7986, "heading": 82.71481, "sats": 8, "batt": 2.9, "frequency": 403.9, "burst_timer": 65535, "snr": 19.0, "user-agent": "Amazon CloudFront", "position": "52.10434,5.19702", "upload_time_delta": -0.752829, "uploader_alt": 10.0, "launch_site": "06260", "launch_site_range_estimate": 1327.4278813819699}, {"software_name": "radiosonde_auto_rx", "software_version": "1.5.5", "uploader_callsign": "PAST2", "uploader_position": "51.5605,5.0", "uploader_antenna": "1/4 wave monopole", "time_received": "2021-09-28T01:09:32.171301Z", "datetime": "2021-09-28T01:09:48.001000Z", "manufacturer": "Vaisala", "type": "RS41", "serial": "S1230514", "subtype": "RS41-SGP", "frame": 6635, "lat": 52.45916, "lon": 6.29179, "alt": 33532.81806, "temp": -42.7, "humidity": 0.6, "pressure": 6.55, "vel_v": -1.84794, "vel_h": 16.35936, "heading": 58.9244, "sats": 8, "batt": 2.5, "frequency": 403.901, "burst_timer": 65535, "snr": 15.2, "user-agent": "Amazon CloudFront", "position": "52.45916,6.29179", "upload_time_delta": -1.487952, "uploader_alt": 2.0, "launch_site": "06260", "launch_site_range_estimate": 1327.4278813819699}, {"software_name": "radiosonde_auto_rx", "software_version": "1.5.6", "uploader_callsign": "PD2SDV_AUTO_RX", "uploader_position": "52.403212,6.6104727", "uploader_antenna": "Vertical", "time_received": "2021-09-28T01:33:22.243376Z", "datetime": "2021-09-28T01:33:38.001000Z", "manufacturer": "Vaisala", "type": "RS41", "serial": "S1230514", "subtype": "RS41-SGP", "frame": 8065, "lat": 52.5604, "lon": 6.57597, "alt": 91.05743, "temp": 10.5, "humidity": 94.9, "pressure": 1014.15, "vel_v": -10.41573, "vel_h": 4.5484, "heading": 27.16732, "sats": 9, "batt": 2.6, "frequency": 403.901, "burst_timer": 29207, "snr": 17.6, "user-agent": "Amazon CloudFront", "position": "52.5604,6.57597", "upload_time_delta": -1.93649, "uploader_alt": 0.0, "launch_site": "06260", "launch_site_range_estimate": 1327.4278813819699}]