[{"software_name": "radiosonde_auto_rx", "software_version": "1.5.1", "uploader_callsign": "BZ-auto_rx", "uploader_position": "52.0,4.2", "uploader_antenna": "1/4 wave monopole", "time_received": "2021-04-25T23:33:52.190454Z", "datetime": "2021-04-25T23:34:08.000000Z", "manufacturer": "Vaisala", "type": "RS41", "serial": "S1310256", "subtype": "RS41", "frame": 11798, "lat": 52.09404, "lon": 5.1592, "alt": 1048.20763, "vel_v": 5.89503, "vel_h": 3.02247, "heading": 283.66562, "sats": 9, "batt": 3, "frequency": 403.902, "burst_timer": 65535, "snr": 7.9, "user-agent": "Amazon CloudFront", "position": "52.09404,5.1592", "upload_time_delta": -0.28786, "uploader_alt": 13, "launch_site": "06260", "launch_site_range_estimate": 1499.604091193162}, {"software_name": "radiosonde_auto_rx", "software_version": "1.5.1", "uploader_callsign": "KS_AUTO_RX", "uploader_position": "50.978,4.964", "uploader_antenna": "1/4 wave monopole", "time_received": "2021-04-26T01:28:05.161207Z", "datetime": "2021-04-26T01:28:21.000000Z", "manufacturer": "Vaisala", "type": "RS41", "serial": "S1310256", "subtype": "RS41-SGP", "frame": 18651, "lat": 51.68116, "lon": 6.27258, "alt": 33222.08703, "temp": -36.8, "humidity": 0.4, "pressure": 6.85, "vel_v": -0.79108, "vel_h": 14.60735, "heading": 62.15316, "sats": 10, "batt": 2.4, "frequency": 403.9, "burst_timer": 65535, "snr": 23.3, "user-agent": "Amazon CloudFront", "position": "51.68116,6.27258", "upload_time_delta": -0.595864, "uploader_alt": 50, "launch_site": "06260", "launch_site_range_estimate": 1499.604091193162}, {"software_name": "radiosonde_auto_rx", "software_version": "1.5.1", "uploader_callsign": "BIOWL1", "uploader_position": "52.014417,8.47351", "uploader_antenna": "SirioCX395", "time_received": "2021-04-26T02:41:58.197571Z", "datetime": "2021-04-26T02:42:14.000000Z", "manufacturer": "Vaisala", "type": "RS41", "serial": "S1310256", "subtype": "RS41-SGP", "frame": 23084, "lat": 51.37888, "lon": 6.90415, "alt": 267.74622, "temp": 5.3, "humidity": 54.9, "pressure": 993.88, "vel_v": -3.13638, "vel_h": 6.15725, "heading": 224.53312, "sats": 10, "batt": 2.6, "frequency": 403.9, "burst_timer": 26229, "snr": 7.3, "user-agent": "Amazon CloudFront", "position": "51.37888,6.90415", "upload_time_delta": -1.031525, "uploader_alt": 340, "launch_site": "06260", "launch_site_range_estimate": 1499.604091193162}]