[{"software_name": "radiosonde_auto_rx", "software_version": "1.5.4", "uploader_callsign": "PA0CAB_AUTORX", "uploader_position": "52.0306,4.32", "uploader_antenna": "10 ele vertical", "time_received": "2021-09-11T23:38:47.303249Z", "datetime": "2021-09-11T23:39:03.001000Z", "manufacturer": "Vaisala", "type": "RS41", "serial": "T1450066", "subtype": "RS41", "frame": 13913, "lat": 52.10119, "lon": 5.17921, "alt": 216.07588, "vel_v": 5.35642, "vel_h": 9.26107, "heading": 66.33661, "sats": 8, "batt": 3.2, "frequency": 403.901, "burst_timer": 65535, "snr": 7.8, "user-agent": "Amazon CloudFront", "position": "52.10119,5.17921", "upload_time_delta": -1.968431, "uploader_alt": 40.0, "launch_site": "06260", "launch_site_range_estimate": 256.583236473937}, {"software_name": "radiosonde_auto_rx", "software_version": "1.5.5", "uploader_callsign": "ONCR16", "uploader_position": "50.8516,4.484", "uploader_antenna": "Sirio CX 395", "time_received": "2021-09-12T01:47:24.238347Z", "datetime": "2021-09-12T01:47:40.000000Z", "manufacturer": "Vaisala", "type": "RS41", "serial": "T1450066", "subtype": "RS41-SGP", "frame": 21630, "lat": 51.97966, "lon": 6.47632, "alt": 34227.19584, "temp": -40.9, "humidity": 0.7, "pressure": 6.64, "vel_v": 0.68319, "vel_h": 15.47811, "heading": 106.00246, "sats": 9, "batt": 2.5, "frequency": 403.9, "burst_timer": 65535, "snr": 15.2, "user-agent": "Amazon CloudFront", "position": "51.97966,6.47632", "upload_time_delta": -1.612392, "uploader_alt": 67.0, "launch_site": "06260", "launch_site_range_estimate": 256.583236473937}, {"software_name": "radiosonde_auto_rx", "software_version": "1.5.5", "uploader_callsign": "MET0W-1", "uploader_position": "51.970823,6.72944", "uploader_antenna": "Mobile Magnetic vert", "time_received": "2021-09-12T02:21:26.170139Z", "datetime": "2021-09-12T02:21:42.000000Z", "manufacturer": "Vaisala", "type": "RS41", "serial": "T1450066", "subtype": "RS41-SGP", "frame": 23672, "lat": 51.94644, "lon": 6.81718, "alt": 150.44864, "temp": 16.2, "humidity": 96.1, "pressure": 1004.8, "vel_v": -11.26425, "vel_h": 5.23687, "heading": 51.49125, "sats": 8, "batt": 2.6, "frequency": 403.9, "burst_timer": 28596, "snr": 11.8, "user-agent": "Amazon CloudFront", "position": "51.94644,6.81718", "upload_time_delta": -0.545625, "uploader_alt": 36.0, "launch_site": "06260", "launch_site_range_estimate": 256.583236473937}]