[{"alt": 932.03608, "batt": 2.9, "burst_timer": 65535, "datetime": "2023-01-05T23:41:21.001000Z", "frame": 757, "frequency": 403.901, "heading": 67.72531, "lat": 52.11034, "launch_site": "06260", "launch_site_range_estimate": 426.642213247822, "lon": 5.20619, "manufacturer": "Vaisala", "position": "52.11034,5.20619", "ref_datetime": "GPS", "ref_position": "GPS", "sats": 8, "serial": "U4254499", "snr": 18.6, "software_name": "radiosonde_auto_rx", "software_version": "1.6.0-beta25", "subtype": "RS41", "time_received": "2023-01-05T23:41:06.565051Z", "type": "RS41", "upload_time_delta": -0.948, "uploader_alt": 7.0, "uploader_antenna": "1/4 wave monopole", "uploader_callsign": "PH1M", "uploader_position": "52.2223,4.5103", "user-agent": "Amazon CloudFront", "vel_h": 17.29702, "vel_v": 4.83207}, {"alt": 30094.8223, "batt": 2.4, "burst_timer": 65535, "datetime": "2023-01-06T01:03:56.001000Z", "frame": 5712, "frequency": 403.901, "heading": 109.24964, "humidity": 2.1, "lat": 52.09344, "launch_site": "06260", "launch_site_range_estimate": 426.642213247822, "lon": 7.5618, "manufacturer": "Vaisala", "position": "52.09344,7.5618", "pressure": 9.88, "sats": 9, "serial": "U4254499", "snr": 14.7, "software_name": "radiosonde_auto_rx", "software_version": "1.5.10", "subtype": "RS41-SGP", "temp": -66.8, "time_received": "2023-01-06T01:03:40.158923Z", "tx_frequency": 403.9, "type": "RS41", "upload_time_delta": -1.023, "uploader_alt": 124.0, "uploader_antenna": "5 dbi vertical", "uploader_callsign": "DL1ZP-14", "uploader_position": "50.1689,8.6767", "user-agent": "Amazon CloudFront", "vel_h": 72.49725, "vel_v": -1.49004}, {"alt": 135.91955, "batt": 2.7, "burst_timer": 27983, "datetime": "2023-01-06T01:52:29.001000Z", "frame": 247, "frequency": 403.9, "heading": 116.77444, "humidity": 96.5, "lat": 52.04804, "lon": 8.63822, "manufacturer": "Vaisala", "position": "52.04804,8.63822", "pressure": 1006.51, "sats": 9, "serial": "U4254499", "snr": 20.0, "software_name": "radiosonde_auto_rx", "software_version": "1.5.10", "subtype": "RS41-SGP", "temp": 9.7, "time_received": "2023-01-06T01:52:13.168177Z", "tx_frequency": 403.9, "type": "RS41", "upload_time_delta": -0.595, "uploader_alt": 340.0, "uploader_antenna": "SirioCX395", "uploader_callsign": "BIOWL1", "uploader_position": "52.014417,8.47351", "user-agent": "Amazon CloudFront", "vel_h": 0.43916, "vel_v": 0.20503}]