[{"version": "autorx-1.4.0", "humidity": "-1.0", "time": "22:48:59", "@timestamp": "2021-02-06T23:33:20.548Z", "uploader_callsign": "DO1AKW-12", "comment": "RS41-SGP R3310204 402.700 MHz 3.0V", "lat": "49.44538", "time_uploaded": "2021-01-20T22:48:43.603012Z", "lon": "11.90962", "alt": "1590", "vel_h": "12.0", "type": "RS41", "frame": "2330", "datetime": "2021-01-20T22:48:43.603012Z", "log_date": "2021-01", "serial": "R3310204", "temp": "-273.0", "@version": "1", "checksum": "186E\\n'", "launch_site": "10771", "launch_site_range_estimate": 1971.6697651759}, {"version": "autorx-1.3.2", "humidity": "0.0", "time": "00:10:45", "@timestamp": "2021-02-06T23:33:07.161Z", "uploader_callsign": "DL3RMG-14", "comment": "RS41-SGP R3310204 402.700 MHz BT 03:57:28 2.5V", "lat": "49.82747", "time_uploaded": "2021-01-21T00:10:30.035845Z", "lon": "13.61396", "alt": "29150", "vel_h": "72.7", "type": "RS41", "frame": "7236", "datetime": "2021-01-21T00:10:30.035845Z", "log_date": "2021-01", "serial": "R3310204", "temp": "-36.6", "@version": "1", "checksum": "4446\\n'", "launch_site": "10771", "launch_site_range_estimate": 1971.6697651759}, {"version": "autorx-1.3.2", "humidity": "73.1", "time": "00:51:13", "@timestamp": "2021-02-06T23:33:17.470Z", "uploader_callsign": "DL3RMG-14", "comment": "RS41-SGP R3310204 402.700 MHz BT 03:16:40 2.4V", "lat": "49.96835", "time_uploaded": "2021-01-21T00:51:00.106348Z", "lon": "14.34463", "alt": "5833", "vel_h": "12.0", "type": "RS41", "frame": "9664", "datetime": "2021-01-21T00:51:00.106348Z", "log_date": "2021-01", "serial": "R3310204", "temp": "-24.3", "@version": "1", "checksum": "B53B\\n'", "launch_site": "10771", "launch_site_range_estimate": 1971.6697651759}]